misso/__init__.py
misso/lsmi.py
misso/misso.py
misso-0.1.dist-info/LICENSE.md
misso-0.1.dist-info/METADATA
misso-0.1.dist-info/WHEEL
misso-0.1.dist-info/top_level.txt
misso-0.1.dist-info/RECORD
