Metadata-Version: 2.1
Name: misso
Version: 0.1
Summary: Python package to compute mutual information matrix
Home-page: https://github.com/AntixK/MISSO
Author: Anand K Subramanian
Author-email: anandkrish894@gmail.com
License: MIT
Platform: UNKNOWN
Classifier: Programming Language :: Python :: 3
Classifier: License :: OSI Approved :: MIT License
Classifier: Operating System :: OS Independent
Classifier: Intended Audience :: Science/Research
Classifier: Natural Language :: English
Requires-Python: >=3.6
Requires-Dist: tqdm (>=4.45.0)
Requires-Dist: numpy (>=1.17.1)
Requires-Dist: matplotlib
Requires-Dist: graphviz (>=0.14.2)
Requires-Dist: joblib (>=0.17.0)
